generic_repo/__init__.py
generic_repo/async_repo.py
generic_repo/filter_helper.py
generic_repo/sync_repo.py
generic_repo-2.0.9.dist-info/METADATA
generic_repo-2.0.9.dist-info/WHEEL
generic_repo-2.0.9.dist-info/licenses/LICENSE
generic_repo-2.0.9.dist-info/RECORD
