Metadata-Version: 2.4
Name: generic-repo
Version: 2.0.9
Summary: A powerful, production-ready Python package for DynamoDB operations with repository pattern (sync and async)
Project-URL: Homepage, https://github.com/subratamal/generic-repo
Project-URL: Repository, https://github.com/subratamal/generic-repo.git
Project-URL: Documentation, https://github.com/subratamal/generic-repo/wiki
Project-URL: Changelog, https://github.com/subratamal/generic-repo/blob/main/CHANGELOG.md
Project-URL: Bug Tracker, https://github.com/subratamal/generic-repo/issues
Author-email: Subrat <06.subrata@gmail.com>
Maintainer-email: Subrat <06.subrata@gmail.com>
License: MIT
License-File: LICENSE
Keywords: async,asyncio,aws,batch-operations,boto3,crud,data-access,database,dynamodb,nosql,orm,repository
Classifier: Development Status :: 5 - Production/Stable
Classifier: Framework :: AsyncIO
Classifier: Intended Audience :: Developers
Classifier: License :: OSI Approved :: MIT License
Classifier: Operating System :: OS Independent
Classifier: Programming Language :: Python :: 3
Classifier: Programming Language :: Python :: 3.9
Classifier: Programming Language :: Python :: 3.10
Classifier: Programming Language :: Python :: 3.11
Classifier: Programming Language :: Python :: 3.12
Classifier: Programming Language :: Python :: 3.13
Classifier: Topic :: Database
Classifier: Topic :: Software Development :: Libraries :: Python Modules
Classifier: Typing :: Typed
Requires-Python: >=3.9
Provides-Extra: dev
Requires-Dist: bandit>=1.7.0; extra == 'dev'
Requires-Dist: build>=0.10.0; extra == 'dev'
Requires-Dist: mypy>=1.0.0; extra == 'dev'
Requires-Dist: pytest-asyncio>=0.21.0; extra == 'dev'
Requires-Dist: pytest-cov>=4.0.0; extra == 'dev'
Requires-Dist: pytest-mock>=3.10.0; extra == 'dev'
Requires-Dist: pytest>=7.0.0; extra == 'dev'
Requires-Dist: ruff>=0.1.0; extra == 'dev'
Requires-Dist: twine>=4.0.0; extra == 'dev'
Requires-Dist: types-boto3>=1.0.0; extra == 'dev'
Provides-Extra: docs
Requires-Dist: myst-parser>=0.18.0; extra == 'docs'
Requires-Dist: sphinx-rtd-theme>=1.2.0; extra == 'docs'
Requires-Dist: sphinx>=5.0.0; extra == 'docs'
Provides-Extra: test
Requires-Dist: pytest-asyncio>=0.21.0; extra == 'test'
Requires-Dist: pytest-cov>=4.0.0; extra == 'test'
Requires-Dist: pytest-mock>=3.10.0; extra == 'test'
Requires-Dist: pytest>=7.0.0; extra == 'test'
